odoo/addons/base_rest_pydantic/README.rst
odoo/addons/base_rest_pydantic/__init__.py
odoo/addons/base_rest_pydantic/__manifest__.py
odoo/addons/base_rest_pydantic/restapi.py
odoo/addons/base_rest_pydantic/i18n/base_rest_datamodel.pot
odoo/addons/base_rest_pydantic/i18n/base_rest_pydantic.pot
odoo/addons/base_rest_pydantic/i18n/it.po
odoo/addons/base_rest_pydantic/readme/CONTRIBUTORS.rst
odoo/addons/base_rest_pydantic/readme/DESCRIPTION.rst
odoo/addons/base_rest_pydantic/readme/USAGE.rst
odoo/addons/base_rest_pydantic/static/description/icon.png
odoo/addons/base_rest_pydantic/static/description/index.html
odoo/addons/base_rest_pydantic/tests/__init__.py
odoo/addons/base_rest_pydantic/tests/test_from_params.py
odoo/addons/base_rest_pydantic/tests/test_response.py
odoo14_addon_base_rest_pydantic-14.0.4.3.4.dist-info/METADATA
odoo14_addon_base_rest_pydantic-14.0.4.3.4.dist-info/WHEEL
odoo14_addon_base_rest_pydantic-14.0.4.3.4.dist-info/top_level.txt
odoo14_addon_base_rest_pydantic-14.0.4.3.4.dist-info/RECORD
