Metadata-Version: 2.1
Name: odoo14-addon-base_rest_pydantic
Version: 14.0.4.3.4
Summary: Pydantic binding for base_rest
Home-page: https://github.com/OCA/rest-framework
Author: ACSONE SA/NV,Odoo Community Association (OCA)
Author-email: support@odoo-community.org
License: LGPL-3
Classifier: Programming Language :: Python
Classifier: Framework :: Odoo
Classifier: Framework :: Odoo :: 14.0
Classifier: License :: OSI Approved :: GNU Lesser General Public License v3 (LGPLv3)
Requires-Python: >=3.6
Requires-Dist: odoo14-addon-base-rest
Requires-Dist: odoo<14.1dev,>=14.0a
Requires-Dist: pydantic<2
